vlmparse/base_model.py
vlmparse/build_doc.py
vlmparse/cli.py
vlmparse/constants.py
vlmparse/converter.py
vlmparse/converter_with_server.py
vlmparse/registries.py
vlmparse/utils.py
vlmparse/clients/chandra.py
vlmparse/clients/deepseekocr.py
vlmparse/clients/docling.py
vlmparse/clients/dotsocr.py
vlmparse/clients/granite_docling.py
vlmparse/clients/hunyuanocr.py
vlmparse/clients/lightonocr.py
vlmparse/clients/mineru.py
vlmparse/clients/mistral_converter.py
vlmparse/clients/nanonetocr.py
vlmparse/clients/olmocr.py
vlmparse/clients/openai_converter.py
vlmparse/clients/paddleocrvl.py
vlmparse/clients/prompts.py
vlmparse/clients/pipe_utils/cleaner.py
vlmparse/clients/pipe_utils/html_to_md_conversion.py
vlmparse/clients/pipe_utils/utils.py
vlmparse/data_model/box.py
vlmparse/data_model/document.py
vlmparse/servers/docker_server.py
vlmparse/servers/model_identity.py
vlmparse/servers/utils.py
vlmparse/st_viewer/fs_nav.py
vlmparse/st_viewer/st_viewer.py
vlmparse-0.1.8.dist-info/licenses/LICENSE
vlmparse-0.1.8.dist-info/METADATA
vlmparse-0.1.8.dist-info/WHEEL
vlmparse-0.1.8.dist-info/entry_points.txt
vlmparse-0.1.8.dist-info/top_level.txt
vlmparse-0.1.8.dist-info/RECORD
