Metadata-Version: 2.4
Name: vlmparse
Version: 0.1.8
Requires-Python: >=3.11.0
License-File: LICENSE
Requires-Dist: devtools>=0.12.2
Requires-Dist: docker>=7.1.0
Requires-Dist: html-to-markdown>=1.9.0
Requires-Dist: httpx>=0.27.0
Requires-Dist: loguru>=0.7.3
Requires-Dist: nest-asyncio>=1.6.0
Requires-Dist: numpy>=2.3.2
Requires-Dist: openai>=1.102.0
Requires-Dist: orjson>=3.11.3
Requires-Dist: pillow>=11.3.0
Requires-Dist: pydantic
Requires-Dist: pypdfium2>=4.30.0
Requires-Dist: fire>=0.7.1
Requires-Dist: lxml>=6.0.2
Requires-Dist: tabulate>=0.9.0
Requires-Dist: beautifulsoup4>=4.14.2
Provides-Extra: dev
Requires-Dist: jupyter; extra == "dev"
Provides-Extra: docling-core
Requires-Dist: docling-core; extra == "docling-core"
Provides-Extra: st-app
Requires-Dist: streamlit>=1.49.0; extra == "st-app"
Provides-Extra: bench
Requires-Dist: html-to-markdown>=1.9.0; extra == "bench"
Requires-Dist: loguru>=0.7.3; extra == "bench"
Requires-Dist: nest-asyncio>=1.6.0; extra == "bench"
Requires-Dist: numpy>=2.3.2; extra == "bench"
Requires-Dist: pillow>=11.3.0; extra == "bench"
Requires-Dist: pydantic; extra == "bench"
Requires-Dist: rapidfuzz>=3.14.0; extra == "bench"
Requires-Dist: unidecode>=1.4.0; extra == "bench"
Requires-Dist: fire>=0.7.1; extra == "bench"
Requires-Dist: lxml>=6.0.2; extra == "bench"
Requires-Dist: datasets>=4.4.1; extra == "bench"
Requires-Dist: openpyxl>=3.1.5; extra == "bench"
Requires-Dist: joblib>=1.5.2; extra == "bench"
Requires-Dist: playwright; extra == "bench"
Requires-Dist: fuzzysearch>=0.8.1; extra == "bench"
Provides-Extra: test
Requires-Dist: pre-commit; extra == "test"
Requires-Dist: pytest; extra == "test"
Requires-Dist: pytest-cov; extra == "test"
Requires-Dist: pytest-mock; extra == "test"
Requires-Dist: ruff; extra == "test"
Requires-Dist: isort; extra == "test"
Requires-Dist: pre-commit; extra == "test"
Dynamic: license-file
